{"cameraMode":{"drawMode":0,"name":"Shaded","section":"Shading Mode"},"sceneLighting":false,"audioPlay":false,"sceneViewState":{"m_AlwaysRefresh":false,"showFog":true,"showSkybox":false,"showFlares":true,"showImageEffects":true,"showParticleSystems":true,"showVisualEffectGraphs":true,"m_FxEnabled":true},"in2DMode":false,"pivot":{"x":-0.01919117569923401,"y":0.42630207538604739,"z":0.020786941051483156},"rotation":{"x":-0.0786324143409729,"y":0.8997114300727844,"z":-0.18191207945346833,"w":-0.38890525698661806},"size":0.7729026079177856,"orthographic":false}