{"cameraMode":{"drawMode":0,"name":"Shaded","section":"Shading Mode"},"sceneLighting":false,"audioPlay":false,"sceneViewState":{"m_AlwaysRefresh":false,"showFog":true,"showSkybox":false,"showFlares":true,"showImageEffects":true,"showParticleSystems":true,"showVisualEffectGraphs":true,"m_FxEnabled":true},"in2DMode":false,"pivot":{"x":-0.5678253173828125,"y":0.28472843766212466,"z":-0.24621786177158357},"rotation":{"x":-0.052851997315883639,"y":-0.7092214226722717,"z":-0.05312928929924965,"w":0.7011378407478333},"size":1.2185512781143189,"orthographic":false}